pydict2class/__init__.py
pydict2class/lib.py
pydict2class-0.0.1.dist-info/LICENSE
pydict2class-0.0.1.dist-info/METADATA
pydict2class-0.0.1.dist-info/WHEEL
pydict2class-0.0.1.dist-info/top_level.txt
pydict2class-0.0.1.dist-info/RECORD
