Metadata-Version: 2.1
Name: pydict2class
Version: 0.0.1
Summary: Dynamically generate classes from JSON or Dicts
Author-email: Dierk-Bent Piening <dierk-bent.piening@mailbox.org>
Project-URL: Homepage, https://github.com/dierk-bentpiening/Dict2Class/
Project-URL: Bug Tracker, https://github.com/dierk-bentpiening/Dict2Class/issues
Classifier: Programming Language :: Python :: 3
Classifier: License :: OSI Approved :: GNU General Public License v3 (GPLv3)
Classifier: Operating System :: OS Independent
Classifier: Topic :: Software Development :: Code Generators
Requires-Python: >=3.7
License-File: LICENSE
